setup.cfg
setup.py
apimodel/__init__.py
apimodel.egg-info/PKG-INFO
apimodel.egg-info/SOURCES.txt
apimodel.egg-info/dependency_links.txt
apimodel.egg-info/top_level.txt