Metadata-Version: 1.0
Name: apimodel
Version: 1.0.0
Summary: API-backed Django-style model
Home-page: http://github.com/ethanmcc/apimodel
Author: Ethan McCreadie
Author-email: ethanmcc@gmail.com
License: UNKNOWN
Keywords: python,django,rest,api,model
Platform: UNKNOWN
